pof/__init__.py
pof/app.py
pof/assets/AG.png
pof/assets/dauphine.png
pof/models/catboost.cbm
pof/models/iso_calibrator_global.pkl
pof/models/iso_calibrator_valid.pkl
pof/models/model_schema.pkl
pof_hackathon-0.0.3.dist-info/licenses/LICENCE
pof_hackathon-0.0.3.dist-info/METADATA
pof_hackathon-0.0.3.dist-info/WHEEL
pof_hackathon-0.0.3.dist-info/entry_points.txt
pof_hackathon-0.0.3.dist-info/top_level.txt
pof_hackathon-0.0.3.dist-info/RECORD
