Metadata-Version: 2.4
Name: POF_Hackathon
Version: 0.0.3
Summary: POF - Probability Of Fraud
Author: Anthony
License: MIT
Requires-Python: >=3.9
License-File: LICENCE
Requires-Dist: pandas<2.4,>=2.0
Requires-Dist: joblib>=1.3
Requires-Dist: catboost>=1.2
Requires-Dist: pillow>=10.0
Requires-Dist: scikit-learn<1.6,>=1.3
Dynamic: license-file
